{
    "hashCacheCheckAccSwitch": 1,
    "default": {
        "cdnList": [
            {
                "K1": 1,
                "K2": 1,
                "P": 150,
                "url": "https://pcdownload-huoshan.aki-game.com/"
            },
            {
                "K1": 1,
                "K2": 1,
                "P": 0,
                "url": "https://pcdownload-qcloud.aki-game.com/"
            },
            {
                "K1": 1,
                "K2": 1,
                "P": 396,
                "url": "https://pcdownload-aliyun.aki-game.com/"
            }
        ],
        "changelog": {},
        "changelogVisible": 0,
        "resourceChunk": {
            "lastMd5": "94f5577044bdcd216896dd0564609585",
            "lastResourceChunkPath": "pcstarter/prod/game/G152/2.2.0/DHM2VYFpJsi33wl2qT3obUWiKDHC9ucT/resourceChunk.json",
            "lastResources": "pcstarter/prod/game/G152/2.2.0/4qOQXRgFtEbYo6glSpYrG6N5yMuscF97/resource.json",
            "lastVersion": "2.2.0",
            "md5": "de1e2ed1178c913651650f1b2fbd6fd7",
            "resourceChunkPath": "pcstarter/prod/game/G152/2.2.1/5DGgbPhdUGgcMWzMJWugPBIQOixs1Em7/resourceChunk.json"
        },
        "resources": "pcstarter/prod/game/G152/2.2.1/WpwvP26jdT38AzADIHmpNI95bpCszODv/resource.json",
        "resourcesBasePath": "pcstarter/prod/game/G152/2.2.1/WpwvP26jdT38AzADIHmpNI95bpCszODv/zip",
        "resourcesDiff": {
            "currentGameInfo": {
                "fileName": "Wuthering Waves.zip",
                "md5": "8db2ee0831aa3a1d83c30c8b555e372b",
                "version": "2.2.1"
            },
            "previousGameInfo": {
                "fileName": "Wuthering Waves.zip",
                "md5": "365552371482e766e841c9e8870460f5",
                "version": "2.2.0"
            }
        },
        "resourcesExcludePath": [],
        "resourcesExcludePathNeedUpdate": [],
        "sampleHashSwitch": 0,
        "version": "2.2.1"
    },
    "predownloadSwitch": 1,
    "RHIOptionSwitch": 1,
    "RHIOptionList": [
        {
            "cmdOption": "-dx12",
            "isShow": 0,
            "text": {}
        },
        {
            "cmdOption": "-dx11",
            "isShow": 1,
            "text": {
                "zh-Hans": "使用DX11启动（游戏异常时选择）",
                "de": "Start mit DX11 (bei Anomalie)",
                "zh-Hant": "使用DX11啟動（遊戲異常時選擇）",
                "ko": "DX11로 시작하기 (게임 에러 시 선택)",
                "ja": "DX11起動（異常発生時に選択）",
                "en": "Launch with DirectX 11 (in case of game anomalies)",
                "fr": "Démarrer en DX11 (à choisir en cas d'anomalie)",
                "es": "Iniciar con DirectX 11 (si hay problemas)"
            }
        }
    ],
    "resourcesLogin": {
        "host": "https://pc-h5sdk-api.kurogame.com",
        "loginSwitch": 1
    },
    "keyFileCheckSwitch": 1,
    "keyFileCheckList": [
        "/Client/Binaries/Win64/Client-Win64-Shipping.exe",
        "/Client/Binaries/Win64/Client-Win64-ShippingBase.dll",
        "/Wuthering Waves.exe",
        "/Client/Binaries/Win64/ThirdParty/KrPcSdk_Mainland/KRSDKRes/KRSDKConfig.json"
    ],
    "chunkDownloadSwitch": 0,
    "checkExeIsRunning": 0,
    "fingerprints": [
        "b63333a20684cc947195443809114156e9e9cd07",
        "9f03afee53588b763e37e897e575b88e2270d507"
    ],
    "experiment": {
        "download": {
            "dropNetworkError": 1,
            "disabledCompressed": 1,
            "dropWrongContentLength": 1,
            "dropWrongContentEncoding": 1
        }
    }
}